README.rst
setup.cfg
setup.py
sentry_auth_crowd/__init__.py
sentry_auth_crowd/backend.py
sentry_auth_crowd/constants.py
sentry_auth_crowd_NWK.egg-info/PKG-INFO
sentry_auth_crowd_NWK.egg-info/SOURCES.txt
sentry_auth_crowd_NWK.egg-info/dependency_links.txt
sentry_auth_crowd_NWK.egg-info/not-zip-safe
sentry_auth_crowd_NWK.egg-info/requires.txt
sentry_auth_crowd_NWK.egg-info/top_level.txt