Metadata-Version: 2.1
Name: sentry-auth-crowd-NWK
Version: 0.7.0
Summary: Crowd authentication provider for Sentry
Home-page: https://github.com/NWKDenmark/sentry-auth-crowd
Author: NWK
Author-email: NWKDenmark@protonmail.com
License: Apache 2.0
Platform: UNKNOWN
Classifier: Intended Audience :: Developers
Classifier: Intended Audience :: System Administrators
Classifier: Operating System :: OS Independent
Classifier: Topic :: Software Development
Provides-Extra: tests
